[
  {
    "year": "23-24",
    "term": "SUMMER",
    "levelOfStatistics": "School",
    "school": "SSCI",
    "department": null,
    "courseGroup": null,
    "courseNumber": null,
    "section": null,
    "courseCode": null,
    "sectionCode": null,
    "surveyName": null,
    "instructorName": null,
    "instructorItsc": null,
    "enrollment": null,
    "responseRate": 0.257,
    "responseRateAdjusted": null,
    "numberOfSectionsEvaluated": 13,
    "courseOverallMean": 4.24,
    "courseOverallMeanAdjusted": null,
    "courseOverallSD": 0.97,
    "courseOverallSDAdjusted": null,
    "instructorOverallMean": 4.48,
    "instructorOverallMeanAdjusted": null,
    "instructorOverallSD": 0.84,
    "instructorOverallSDAdjusted": null
  },
  {
    "year": "23-24",
    "term": "SUMMER",
    "levelOfStatistics": "Dept / Course Group",
    "school": "SSCI",
    "department": "BTEC",
    "courseGroup": null,
    "courseNumber": null,
    "section": null,
    "courseCode": null,
    "sectionCode": null,
    "surveyName": null,
    "instructorName": null,
    "instructorItsc": null,
    "enrollment": null,
    "responseRate": 0.308,
    "responseRateAdjusted": null,
    "lowResponseRateIndicator": true,
    "numberOfSectionsEvaluated": 1,
    "courseOverallMean": 4.55,
    "courseOverallMeanAdjusted": null,
    "courseOverallSD": 0.6,
    "courseOverallSDAdjusted": null,
    "instructorOverallMean": 4.65,
    "instructorOverallMeanAdjusted": null,
    "instructorOverallSD": 0.58,
    "instructorOverallSDAdjusted": null
  },
  {
    "year": "23-24",
    "term": "SUMMER",
    "levelOfStatistics": "Dept / Course Group",
    "school": "SSCI",
    "department": "CHEM",
    "courseGroup": null,
    "courseNumber": null,
    "section": null,
    "courseCode": null,
    "sectionCode": null,
    "surveyName": null,
    "instructorName": null,
    "instructorItsc": null,
    "enrollment": null,
    "responseRate": 0.279,
    "responseRateAdjusted": null,
    "lowResponseRateIndicator": true,
    "numberOfSectionsEvaluated": 2,
    "courseOverallMean": 4.05,
    "courseOverallMeanAdjusted": null,
    "courseOverallSD": 1.22,
    "courseOverallSDAdjusted": null,
    "instructorOverallMean": 4.52,
    "instructorOverallMeanAdjusted": null,
    "instructorOverallSD": 0.65,
    "instructorOverallSDAdjusted": null
  },
  {
    "year": "23-24",
    "term": "SUMMER",
    "levelOfStatistics": "Dept / Course Group",
    "school": "SSCI",
    "department": "LIFS",
    "courseGroup": null,
    "courseNumber": null,
    "section": null,
    "courseCode": null,
    "sectionCode": null,
    "surveyName": null,
    "instructorName": null,
    "instructorItsc": null,
    "enrollment": null,
    "responseRate": 0.27,
    "responseRateAdjusted": null,
    "lowResponseRateIndicator": true,
    "numberOfSectionsEvaluated": 1,
    "courseOverallMean": 4.3,
    "courseOverallMeanAdjusted": null,
    "courseOverallSD": 0.48,
    "courseOverallSDAdjusted": null,
    "instructorOverallMean": 4.6,
    "instructorOverallMeanAdjusted": null,
    "instructorOverallSD": 0.5,
    "instructorOverallSDAdjusted": null
  },
  {
    "year": "23-24",
    "term": "SUMMER",
    "levelOfStatistics": "Dept / Course Group",
    "school": "SSCI",
    "department": "MATH",
    "courseGroup": null,
    "courseNumber": null,
    "section": null,
    "courseCode": null,
    "sectionCode": null,
    "surveyName": null,
    "instructorName": null,
    "instructorItsc": null,
    "enrollment": null,
    "responseRate": 0.281,
    "responseRateAdjusted": null,
    "numberOfSectionsEvaluated": 3,
    "courseOverallMean": 3.85,
    "courseOverallMeanAdjusted": null,
    "courseOverallSD": 1.27,
    "courseOverallSDAdjusted": null,
    "instructorOverallMean": 3.82,
    "instructorOverallMeanAdjusted": null,
    "instructorOverallSD": 1.48,
    "instructorOverallSDAdjusted": null
  },
  {
    "year": "23-24",
    "term": "SUMMER",
    "levelOfStatistics": "Dept / Course Group",
    "school": "SSCI",
    "department": "PHYS",
    "courseGroup": null,
    "courseNumber": null,
    "section": null,
    "courseCode": null,
    "sectionCode": null,
    "surveyName": null,
    "instructorName": null,
    "instructorItsc": null,
    "enrollment": null,
    "responseRate": 0.249,
    "responseRateAdjusted": null,
    "numberOfSectionsEvaluated": 4,
    "courseOverallMean": 4.34,
    "courseOverallMeanAdjusted": null,
    "courseOverallSD": 0.78,
    "courseOverallSDAdjusted": null,
    "instructorOverallMean": 4.5,
    "instructorOverallMeanAdjusted": null,
    "instructorOverallSD": 0.59,
    "instructorOverallSDAdjusted": null
  },
  {
    "year": "23-24",
    "term": "SUMMER",
    "levelOfStatistics": "Dept / Course Group",
    "school": "SSCI",
    "department": "MAFS",
    "courseGroup": null,
    "courseNumber": null,
    "section": null,
    "courseCode": null,
    "sectionCode": null,
    "surveyName": null,
    "instructorName": null,
    "instructorItsc": null,
    "enrollment": null,
    "responseRate": 0.172,
    "responseRateAdjusted": null,
    "lowResponseRateIndicator": true,
    "numberOfSectionsEvaluated": 2,
    "courseOverallMean": 4.73,
    "courseOverallMeanAdjusted": null,
    "courseOverallSD": 0.46,
    "courseOverallSDAdjusted": null,
    "instructorOverallMean": 4.8,
    "instructorOverallMeanAdjusted": null,
    "instructorOverallSD": 0.41,
    "instructorOverallSDAdjusted": null
  },
  {
    "year": "23-24",
    "term": "SUMMER",
    "levelOfStatistics": "Course",
    "school": "SSCI",
    "department": "BTEC",
    "courseGroup": "BTEC",
    "courseNumber": "5210",
    "section": null,
    "courseCode": "23-24-SUMMER-BTEC-5210",
    "sectionCode": null,
    "surveyName": null,
    "instructorName": null,
    "instructorItsc": null,
    "enrollment": null,
    "responseRate": 0.308,
    "responseRateAdjusted": null,
    "lowResponseRateIndicator": true,
    "numberOfSectionsEvaluated": 1,
    "courseOverallMean": 4.55,
    "courseOverallMeanAdjusted": null,
    "courseOverallSD": 0.6,
    "courseOverallSDAdjusted": null,
    "instructorOverallMean": 4.65,
    "instructorOverallMeanAdjusted": null,
    "instructorOverallSD": 0.58,
    "instructorOverallSDAdjusted": null
  },
  {
    "year": "23-24",
    "term": "SUMMER",
    "levelOfStatistics": "Section",
    "school": "SSCI",
    "department": "BTEC",
    "courseGroup": "BTEC",
    "courseNumber": "5210",
    "section": "L1",
    "courseCode": "23-24-SUMMER-BTEC-5210",
    "sectionCode": "23-24-SUMMER-BTEC-5210-L1",
    "surveyName": null,
    "instructorName": null,
    "instructorItsc": null,
    "enrollment": 65,
    "responseRate": 0.308,
    "responseRateAdjusted": null,
    "lowResponseRateIndicator": true,
    "numberOfSectionsEvaluated": null,
    "courseOverallMean": 4.55,
    "courseOverallMeanAdjusted": null,
    "courseOverallSD": 0.6,
    "courseOverallSDAdjusted": null,
    "instructorOverallMean": 4.65,
    "instructorOverallMeanAdjusted": null,
    "instructorOverallSD": 0.58,
    "instructorOverallSDAdjusted": null
  },
  {
    "year": "23-24",
    "term": "SUMMER",
    "levelOfStatistics": "Instructor",
    "school": "SSCI",
    "department": "BTEC",
    "courseGroup": "BTEC",
    "courseNumber": "5210",
    "section": "L1",
    "courseCode": "23-24-SUMMER-BTEC-5210",
    "sectionCode": "23-24-SUMMER-BTEC-5210-L1",
    "surveyName": "23-24-SUMMER-BTEC-5210-L1-SI",
    "instructorName": "CHUNG, Kenny Ka Kin",
    "instructorItsc": "bckchung",
    "enrollment": 65,
    "responseRate": 0.308,
    "responseRateAdjusted": 0.277,
    "lowResponseRateIndicator": true,
    "numberOfSectionsEvaluated": null,
    "courseOverallMean": 4.55,
    "courseOverallMeanAdjusted": 4.61,
    "courseOverallSD": 0.6,
    "courseOverallSDAdjusted": 0.5,
    "instructorOverallMean": 4.65,
    "instructorOverallMeanAdjusted": 4.72,
    "instructorOverallSD": 0.59,
    "instructorOverallSDAdjusted": 0.46
  },
  {
    "year": "23-24",
    "term": "SUMMER",
    "levelOfStatistics": "Instructor",
    "school": "SSCI",
    "department": "BTEC",
    "courseGroup": "BTEC",
    "courseNumber": "5210",
    "section": "L1",
    "courseCode": "23-24-SUMMER-BTEC-5210",
    "sectionCode": "23-24-SUMMER-BTEC-5210-L1",
    "surveyName": "23-24-SUMMER-BTEC-5210-L1-SI",
    "instructorName": "HIRANO, Yukinori",
    "instructorItsc": "yukinori",
    "enrollment": 65,
    "responseRate": 0.308,
    "responseRateAdjusted": 0.277,
    "lowResponseRateIndicator": true,
    "numberOfSectionsEvaluated": null,
    "courseOverallMean": 4.55,
    "courseOverallMeanAdjusted": 4.61,
    "courseOverallSD": 0.6,
    "courseOverallSDAdjusted": 0.5,
    "instructorOverallMean": 4.65,
    "instructorOverallMeanAdjusted": 4.72,
    "instructorOverallSD": 0.59,
    "instructorOverallSDAdjusted": 0.46
  },
  {
    "year": "23-24",
    "term": "SUMMER",
    "levelOfStatistics": "Instructor",
    "school": "SSCI",
    "department": "BTEC",
    "courseGroup": "BTEC",
    "courseNumber": "5210",
    "section": "L1",
    "courseCode": "23-24-SUMMER-BTEC-5210",
    "sectionCode": "23-24-SUMMER-BTEC-5210-L1",
    "surveyName": "23-24-SUMMER-BTEC-5210-L1-SI",
    "instructorName": "NGUYEN, Tuan Anh",
    "instructorItsc": "tuananh",
    "enrollment": 65,
    "responseRate": 0.308,
    "responseRateAdjusted": 0.277,
    "lowResponseRateIndicator": true,
    "numberOfSectionsEvaluated": null,
    "courseOverallMean": 4.55,
    "courseOverallMeanAdjusted": 4.61,
    "courseOverallSD": 0.6,
    "courseOverallSDAdjusted": 0.5,
    "instructorOverallMean": 4.6,
    "instructorOverallMeanAdjusted": 4.67,
    "instructorOverallSD": 0.6,
    "instructorOverallSDAdjusted": 0.49
  },
  {
    "year": "23-24",
    "term": "SUMMER",
    "levelOfStatistics": "Instructor",
    "school": "SSCI",
    "department": "BTEC",
    "courseGroup": "BTEC",
    "courseNumber": "5210",
    "section": "L1",
    "courseCode": "23-24-SUMMER-BTEC-5210",
    "sectionCode": "23-24-SUMMER-BTEC-5210-L1",
    "surveyName": "23-24-SUMMER-BTEC-5210-L1-SI",
    "instructorName": "POON, Randy Yat Choi",
    "instructorItsc": "rycpoon",
    "enrollment": 65,
    "responseRate": 0.308,
    "responseRateAdjusted": 0.277,
    "lowResponseRateIndicator": true,
    "numberOfSectionsEvaluated": null,
    "courseOverallMean": 4.55,
    "courseOverallMeanAdjusted": 4.61,
    "courseOverallSD": 0.6,
    "courseOverallSDAdjusted": 0.5,
    "instructorOverallMean": 4.7,
    "instructorOverallMeanAdjusted": 4.78,
    "instructorOverallSD": 0.57,
    "instructorOverallSDAdjusted": 0.43
  },
  {
    "year": "23-24",
    "term": "SUMMER",
    "levelOfStatistics": "Instructor",
    "school": "SSCI",
    "department": "BTEC",
    "courseGroup": "BTEC",
    "courseNumber": "5210",
    "section": "L1",
    "courseCode": "23-24-SUMMER-BTEC-5210",
    "sectionCode": "23-24-SUMMER-BTEC-5210-L1",
    "surveyName": "23-24-SUMMER-BTEC-5210-L1-SI",
    "instructorName": "WU, Zhenguo",
    "instructorItsc": "bczgwu",
    "enrollment": 65,
    "responseRate": 0.308,
    "responseRateAdjusted": 0.277,
    "lowResponseRateIndicator": true,
    "numberOfSectionsEvaluated": null,
    "courseOverallMean": 4.55,
    "courseOverallMeanAdjusted": 4.61,
    "courseOverallSD": 0.6,
    "courseOverallSDAdjusted": 0.5,
    "instructorOverallMean": 4.65,
    "instructorOverallMeanAdjusted": 4.72,
    "instructorOverallSD": 0.59,
    "instructorOverallSDAdjusted": 0.46
  },
  {
    "year": "23-24",
    "term": "SUMMER",
    "levelOfStatistics": "Course",
    "school": "SSCI",
    "department": "CHEM",
    "courseGroup": "CHEM",
    "courseNumber": "1002",
    "section": null,
    "courseCode": "23-24-SUMMER-CHEM-1002",
    "sectionCode": null,
    "surveyName": null,
    "instructorName": null,
    "instructorItsc": null,
    "enrollment": null,
    "responseRate": 0.232,
    "responseRateAdjusted": 0.196,
    "lowResponseRateIndicator": true,
    "numberOfSectionsEvaluated": 1,
    "courseOverallMean": 4.15,
    "courseOverallMeanAdjusted": 4.36,
    "courseOverallSD": 1.34,
    "courseOverallSDAdjusted": 1.03,
    "instructorOverallMean": 4.54,
    "instructorOverallMeanAdjusted": 4.64,
    "instructorOverallSD": 0.78,
    "instructorOverallSDAdjusted": 0.67
  },
  {
    "year": "23-24",
    "term": "SUMMER",
    "levelOfStatistics": "Section",
    "school": "SSCI",
    "department": "CHEM",
    "courseGroup": "CHEM",
    "courseNumber": "1002",
    "section": "L1",
    "courseCode": "23-24-SUMMER-CHEM-1002",
    "sectionCode": "23-24-SUMMER-CHEM-1002-L1",
    "surveyName": null,
    "instructorName": null,
    "instructorItsc": null,
    "enrollment": 56,
    "responseRate": 0.232,
    "responseRateAdjusted": 0.196,
    "lowResponseRateIndicator": true,
    "numberOfSectionsEvaluated": null,
    "courseOverallMean": 4.15,
    "courseOverallMeanAdjusted": 4.36,
    "courseOverallSD": 1.34,
    "courseOverallSDAdjusted": 1.03,
    "instructorOverallMean": 4.54,
    "instructorOverallMeanAdjusted": 4.64,
    "instructorOverallSD": 0.78,
    "instructorOverallSDAdjusted": 0.67
  },
  {
    "year": "23-24",
    "term": "SUMMER",
    "levelOfStatistics": "Instructor",
    "school": "SSCI",
    "department": "CHEM",
    "courseGroup": "CHEM",
    "courseNumber": "1002",
    "section": "L1",
    "courseCode": "23-24-SUMMER-CHEM-1002",
    "sectionCode": "23-24-SUMMER-CHEM-1002-L1",
    "surveyName": "23-24-SUMMER-CHEM-1002-L1-SI",
    "instructorName": "CHAN, Ho Wai",
    "instructorItsc": "chanhw",
    "enrollment": 56,
    "responseRate": 0.232,
    "responseRateAdjusted": 0.196,
    "lowResponseRateIndicator": true,
    "numberOfSectionsEvaluated": null,
    "courseOverallMean": 4.15,
    "courseOverallMeanAdjusted": 4.36,
    "courseOverallSD": 1.34,
    "courseOverallSDAdjusted": 1.03,
    "instructorOverallMean": 4.54,
    "instructorOverallMeanAdjusted": 4.64,
    "instructorOverallSD": 0.78,
    "instructorOverallSDAdjusted": 0.67
  },
  {
    "year": "23-24",
    "term": "SUMMER",
    "levelOfStatistics": "Course",
    "school": "SSCI",
    "department": "CHEM",
    "courseGroup": "CHEM",
    "courseNumber": "1008",
    "section": null,
    "courseCode": "23-24-SUMMER-CHEM-1008",
    "sectionCode": null,
    "surveyName": null,
    "instructorName": null,
    "instructorItsc": null,
    "enrollment": null,
    "responseRate": 0.5,
    "responseRateAdjusted": null,
    "lowResponseRateIndicator": true,
    "numberOfSectionsEvaluated": 1,
    "courseOverallMean": 3.83,
    "courseOverallMeanAdjusted": null,
    "courseOverallSD": 0.98,
    "courseOverallSDAdjusted": null,
    "instructorOverallMean": 4.5,
    "instructorOverallMeanAdjusted": null,
    "instructorOverallSD": 0.52,
    "instructorOverallSDAdjusted": null
  },
  {
    "year": "23-24",
    "term": "SUMMER",
    "levelOfStatistics": "Section",
    "school": "SSCI",
    "department": "CHEM",
    "courseGroup": "CHEM",
    "courseNumber": "1008",
    "section": "L1",
    "courseCode": "23-24-SUMMER-CHEM-1008",
    "sectionCode": "23-24-SUMMER-CHEM-1008-L1",
    "surveyName": null,
    "instructorName": null,
    "instructorItsc": null,
    "enrollment": 12,
    "responseRate": 0.5,
    "responseRateAdjusted": null,
    "lowResponseRateIndicator": true,
    "numberOfSectionsEvaluated": null,
    "courseOverallMean": 3.83,
    "courseOverallMeanAdjusted": null,
    "courseOverallSD": 0.98,
    "courseOverallSDAdjusted": null,
    "instructorOverallMean": 4.5,
    "instructorOverallMeanAdjusted": null,
    "instructorOverallSD": 0.52,
    "instructorOverallSDAdjusted": null
  },
  {
    "year": "23-24",
    "term": "SUMMER",
    "levelOfStatistics": "Instructor",
    "school": "SSCI",
    "department": "CHEM",
    "courseGroup": "CHEM",
    "courseNumber": "1008",
    "section": "L1",
    "courseCode": "23-24-SUMMER-CHEM-1008",
    "sectionCode": "23-24-SUMMER-CHEM-1008-L1",
    "surveyName": "23-24-SUMMER-CHEM-1008-L1-SI",
    "instructorName": "SHEONG, Fu Kit",
    "instructorItsc": "chemfksheong",
    "enrollment": 12,
    "responseRate": 0.5,
    "responseRateAdjusted": 0.333,
    "lowResponseRateIndicator": true,
    "numberOfSectionsEvaluated": null,
    "courseOverallMean": 3.83,
    "courseOverallMeanAdjusted": 4,
    "courseOverallSD": 0.98,
    "courseOverallSDAdjusted": 0,
    "instructorOverallMean": 4.5,
    "instructorOverallMeanAdjusted": 4.5,
    "instructorOverallSD": 0.55,
    "instructorOverallSDAdjusted": 0.58
  },
  {
    "year": "23-24",
    "term": "SUMMER",
    "levelOfStatistics": "Instructor",
    "school": "SSCI",
    "department": "CHEM",
    "courseGroup": "CHEM",
    "courseNumber": "1008",
    "section": "L1",
    "courseCode": "23-24-SUMMER-CHEM-1008",
    "sectionCode": "23-24-SUMMER-CHEM-1008-L1",
    "surveyName": "23-24-SUMMER-CHEM-1008-L1-SI",
    "instructorName": "TSANG, Ming Wai Emily",
    "instructorItsc": "chetsang",
    "enrollment": 12,
    "responseRate": 0.5,
    "responseRateAdjusted": 0.333,
    "lowResponseRateIndicator": true,
    "numberOfSectionsEvaluated": null,
    "courseOverallMean": 3.83,
    "courseOverallMeanAdjusted": 4,
    "courseOverallSD": 0.98,
    "courseOverallSDAdjusted": 0,
    "instructorOverallMean": 4.5,
    "instructorOverallMeanAdjusted": 4.5,
    "instructorOverallSD": 0.55,
    "instructorOverallSDAdjusted": 0.58
  },
  {
    "year": "23-24",
    "term": "SUMMER",
    "levelOfStatistics": "Course",
    "school": "SSCI",
    "department": "LIFS",
    "courseGroup": "LIFS",
    "courseNumber": "1020",
    "section": null,
    "courseCode": "23-24-SUMMER-LIFS-1020",
    "sectionCode": null,
    "surveyName": null,
    "instructorName": null,
    "instructorItsc": null,
    "enrollment": null,
    "responseRate": 0.27,
    "responseRateAdjusted": null,
    "lowResponseRateIndicator": true,
    "numberOfSectionsEvaluated": 1,
    "courseOverallMean": 4.3,
    "courseOverallMeanAdjusted": null,
    "courseOverallSD": 0.48,
    "courseOverallSDAdjusted": null,
    "instructorOverallMean": 4.6,
    "instructorOverallMeanAdjusted": null,
    "instructorOverallSD": 0.5,
    "instructorOverallSDAdjusted": null
  },
  {
    "year": "23-24",
    "term": "SUMMER",
    "levelOfStatistics": "Section",
    "school": "SSCI",
    "department": "LIFS",
    "courseGroup": "LIFS",
    "courseNumber": "1020",
    "section": "L1",
    "courseCode": "23-24-SUMMER-LIFS-1020",
    "sectionCode": "23-24-SUMMER-LIFS-1020-L1",
    "surveyName": null,
    "instructorName": null,
    "instructorItsc": null,
    "enrollment": 37,
    "responseRate": 0.27,
    "responseRateAdjusted": null,
    "lowResponseRateIndicator": true,
    "numberOfSectionsEvaluated": null,
    "courseOverallMean": 4.3,
    "courseOverallMeanAdjusted": null,
    "courseOverallSD": 0.48,
    "courseOverallSDAdjusted": null,
    "instructorOverallMean": 4.6,
    "instructorOverallMeanAdjusted": null,
    "instructorOverallSD": 0.5,
    "instructorOverallSDAdjusted": null
  },
  {
    "year": "23-24",
    "term": "SUMMER",
    "levelOfStatistics": "Instructor",
    "school": "SSCI",
    "department": "LIFS",
    "courseGroup": "LIFS",
    "courseNumber": "1020",
    "section": "L1",
    "courseCode": "23-24-SUMMER-LIFS-1020",
    "sectionCode": "23-24-SUMMER-LIFS-1020-L1",
    "surveyName": "23-24-SUMMER-LIFS-1020-L1-SI",
    "instructorName": "LAM, Y Philip",
    "instructorItsc": "ylam",
    "enrollment": 37,
    "responseRate": 0.27,
    "responseRateAdjusted": 0.216,
    "lowResponseRateIndicator": true,
    "numberOfSectionsEvaluated": null,
    "courseOverallMean": 4.3,
    "courseOverallMeanAdjusted": 4.25,
    "courseOverallSD": 0.48,
    "courseOverallSDAdjusted": 0.46,
    "instructorOverallMean": 4.7,
    "instructorOverallMeanAdjusted": 4.75,
    "instructorOverallSD": 0.48,
    "instructorOverallSDAdjusted": 0.46
  },
  {
    "year": "23-24",
    "term": "SUMMER",
    "levelOfStatistics": "Instructor",
    "school": "SSCI",
    "department": "LIFS",
    "courseGroup": "LIFS",
    "courseNumber": "1020",
    "section": "L1",
    "courseCode": "23-24-SUMMER-LIFS-1020",
    "sectionCode": "23-24-SUMMER-LIFS-1020-L1",
    "surveyName": "23-24-SUMMER-LIFS-1020-L1-SI",
    "instructorName": "TANG, Jessica Ce Mun",
    "instructorItsc": "bocemun",
    "enrollment": 37,
    "responseRate": 0.27,
    "responseRateAdjusted": 0.216,
    "lowResponseRateIndicator": true,
    "numberOfSectionsEvaluated": null,
    "courseOverallMean": 4.3,
    "courseOverallMeanAdjusted": 4.25,
    "courseOverallSD": 0.48,
    "courseOverallSDAdjusted": 0.46,
    "instructorOverallMean": 4.5,
    "instructorOverallMeanAdjusted": 4.5,
    "instructorOverallSD": 0.53,
    "instructorOverallSDAdjusted": 0.53
  },
  {
    "year": "23-24",
    "term": "SUMMER",
    "levelOfStatistics": "Course",
    "school": "SSCI",
    "department": "MATH",
    "courseGroup": "MATH",
    "courseNumber": "2111",
    "section": null,
    "courseCode": "23-24-SUMMER-MATH-2111",
    "sectionCode": null,
    "surveyName": null,
    "instructorName": null,
    "instructorItsc": null,
    "enrollment": null,
    "responseRate": 0.28,
    "responseRateAdjusted": 0.24,
    "lowResponseRateIndicator": true,
    "numberOfSectionsEvaluated": 1,
    "courseOverallMean": 2.79,
    "courseOverallMeanAdjusted": 2.75,
    "courseOverallSD": 1.42,
    "courseOverallSDAdjusted": 1.29,
    "instructorOverallMean": 2.5,
    "instructorOverallMeanAdjusted": 2.42,
    "instructorOverallSD": 1.61,
    "instructorOverallSDAdjusted": 1.51
  },
  {
    "year": "23-24",
    "term": "SUMMER",
    "levelOfStatistics": "Section",
    "school": "SSCI",
    "department": "MATH",
    "courseGroup": "MATH",
    "courseNumber": "2111",
    "section": "L1",
    "courseCode": "23-24-SUMMER-MATH-2111",
    "sectionCode": "23-24-SUMMER-MATH-2111-L1",
    "surveyName": null,
    "instructorName": null,
    "instructorItsc": null,
    "enrollment": 50,
    "responseRate": 0.28,
    "responseRateAdjusted": 0.24,
    "lowResponseRateIndicator": true,
    "numberOfSectionsEvaluated": null,
    "courseOverallMean": 2.79,
    "courseOverallMeanAdjusted": 2.75,
    "courseOverallSD": 1.42,
    "courseOverallSDAdjusted": 1.29,
    "instructorOverallMean": 2.5,
    "instructorOverallMeanAdjusted": 2.42,
    "instructorOverallSD": 1.61,
    "instructorOverallSDAdjusted": 1.51
  },
  {
    "year": "23-24",
    "term": "SUMMER",
    "levelOfStatistics": "Instructor",
    "school": "SSCI",
    "department": "MATH",
    "courseGroup": "MATH",
    "courseNumber": "2111",
    "section": "L1",
    "courseCode": "23-24-SUMMER-MATH-2111",
    "sectionCode": "23-24-SUMMER-MATH-2111-L1",
    "surveyName": "23-24-SUMMER-MATH-2111-L1-SI",
    "instructorName": "WANG, Xiaoyu",
    "instructorItsc": "maxywang",
    "enrollment": 50,
    "responseRate": 0.28,
    "responseRateAdjusted": 0.24,
    "lowResponseRateIndicator": true,
    "numberOfSectionsEvaluated": null,
    "courseOverallMean": 2.79,
    "courseOverallMeanAdjusted": 2.75,
    "courseOverallSD": 1.42,
    "courseOverallSDAdjusted": 1.29,
    "instructorOverallMean": 2.5,
    "instructorOverallMeanAdjusted": 2.42,
    "instructorOverallSD": 1.61,
    "instructorOverallSDAdjusted": 1.51
  },
  {
    "year": "23-24",
    "term": "SUMMER",
    "levelOfStatistics": "Course",
    "school": "SSCI",
    "department": "MATH",
    "courseGroup": "MATH",
    "courseNumber": "2411",
    "section": null,
    "courseCode": "23-24-SUMMER-MATH-2411",
    "sectionCode": null,
    "surveyName": null,
    "instructorName": null,
    "instructorItsc": null,
    "enrollment": null,
    "responseRate": 0.38,
    "responseRateAdjusted": 0.34,
    "lowResponseRateIndicator": true,
    "numberOfSectionsEvaluated": 1,
    "courseOverallMean": 4.47,
    "courseOverallMeanAdjusted": 4.47,
    "courseOverallSD": 0.51,
    "courseOverallSDAdjusted": 0.51,
    "instructorOverallMean": 4.68,
    "instructorOverallMeanAdjusted": 4.71,
    "instructorOverallSD": 0.48,
    "instructorOverallSDAdjusted": 0.47
  },
  {
    "year": "23-24",
    "term": "SUMMER",
    "levelOfStatistics": "Section",
    "school": "SSCI",
    "department": "MATH",
    "courseGroup": "MATH",
    "courseNumber": "2411",
    "section": "L1",
    "courseCode": "23-24-SUMMER-MATH-2411",
    "sectionCode": "23-24-SUMMER-MATH-2411-L1",
    "surveyName": null,
    "instructorName": null,
    "instructorItsc": null,
    "enrollment": 50,
    "responseRate": 0.38,
    "responseRateAdjusted": 0.34,
    "lowResponseRateIndicator": true,
    "numberOfSectionsEvaluated": null,
    "courseOverallMean": 4.47,
    "courseOverallMeanAdjusted": 4.47,
    "courseOverallSD": 0.51,
    "courseOverallSDAdjusted": 0.51,
    "instructorOverallMean": 4.68,
    "instructorOverallMeanAdjusted": 4.71,
    "instructorOverallSD": 0.48,
    "instructorOverallSDAdjusted": 0.47
  },
  {
    "year": "23-24",
    "term": "SUMMER",
    "levelOfStatistics": "Instructor",
    "school": "SSCI",
    "department": "MATH",
    "courseGroup": "MATH",
    "courseNumber": "2411",
    "section": "L1",
    "courseCode": "23-24-SUMMER-MATH-2411",
    "sectionCode": "23-24-SUMMER-MATH-2411-L1",
    "surveyName": "23-24-SUMMER-MATH-2411-L1-SI",
    "instructorName": "YAO, Jing",
    "instructorItsc": "majyao",
    "enrollment": 50,
    "responseRate": 0.38,
    "responseRateAdjusted": 0.34,
    "lowResponseRateIndicator": true,
    "numberOfSectionsEvaluated": null,
    "courseOverallMean": 4.47,
    "courseOverallMeanAdjusted": 4.47,
    "courseOverallSD": 0.51,
    "courseOverallSDAdjusted": 0.51,
    "instructorOverallMean": 4.68,
    "instructorOverallMeanAdjusted": 4.71,
    "instructorOverallSD": 0.48,
    "instructorOverallSDAdjusted": 0.47
  },
  {
    "year": "23-24",
    "term": "SUMMER",
    "levelOfStatistics": "Course",
    "school": "SSCI",
    "department": "MATH",
    "courseGroup": "MATH",
    "courseNumber": "2421",
    "section": null,
    "courseCode": "23-24-SUMMER-MATH-2421",
    "sectionCode": null,
    "surveyName": null,
    "instructorName": null,
    "instructorItsc": null,
    "enrollment": null,
    "responseRate": 0.154,
    "responseRateAdjusted": 0.103,
    "lowResponseRateIndicator": true,
    "numberOfSectionsEvaluated": 1,
    "courseOverallMean": 4.33,
    "courseOverallMeanAdjusted": 4.5,
    "courseOverallSD": 1.03,
    "courseOverallSDAdjusted": 1,
    "instructorOverallMean": 4.17,
    "instructorOverallMeanAdjusted": 4.5,
    "instructorOverallSD": 1.17,
    "instructorOverallSDAdjusted": 0.58
  },
  {
    "year": "23-24",
    "term": "SUMMER",
    "levelOfStatistics": "Section",
    "school": "SSCI",
    "department": "MATH",
    "courseGroup": "MATH",
    "courseNumber": "2421",
    "section": "L1",
    "courseCode": "23-24-SUMMER-MATH-2421",
    "sectionCode": "23-24-SUMMER-MATH-2421-L1",
    "surveyName": null,
    "instructorName": null,
    "instructorItsc": null,
    "enrollment": 39,
    "responseRate": 0.154,
    "responseRateAdjusted": 0.103,
    "lowResponseRateIndicator": true,
    "numberOfSectionsEvaluated": null,
    "courseOverallMean": 4.33,
    "courseOverallMeanAdjusted": 4.5,
    "courseOverallSD": 1.03,
    "courseOverallSDAdjusted": 1,
    "instructorOverallMean": 4.17,
    "instructorOverallMeanAdjusted": 4.5,
    "instructorOverallSD": 1.17,
    "instructorOverallSDAdjusted": 0.58
  },
  {
    "year": "23-24",
    "term": "SUMMER",
    "levelOfStatistics": "Instructor",
    "school": "SSCI",
    "department": "MATH",
    "courseGroup": "MATH",
    "courseNumber": "2421",
    "section": "L1",
    "courseCode": "23-24-SUMMER-MATH-2421",
    "sectionCode": "23-24-SUMMER-MATH-2421-L1",
    "surveyName": "23-24-SUMMER-MATH-2421-L1-SI",
    "instructorName": "YU, Chi Wai",
    "instructorItsc": "macwyu",
    "enrollment": 39,
    "responseRate": 0.154,
    "responseRateAdjusted": 0.103,
    "lowResponseRateIndicator": true,
    "numberOfSectionsEvaluated": null,
    "courseOverallMean": 4.33,
    "courseOverallMeanAdjusted": 4.5,
    "courseOverallSD": 1.03,
    "courseOverallSDAdjusted": 1,
    "instructorOverallMean": 4.17,
    "instructorOverallMeanAdjusted": 4.5,
    "instructorOverallSD": 1.17,
    "instructorOverallSDAdjusted": 0.58
  },
  {
    "year": "23-24",
    "term": "SUMMER",
    "levelOfStatistics": "Course",
    "school": "SSCI",
    "department": "PHYS",
    "courseGroup": "PHYS",
    "courseNumber": "1002",
    "section": null,
    "courseCode": "23-24-SUMMER-PHYS-1002",
    "sectionCode": null,
    "surveyName": null,
    "instructorName": null,
    "instructorItsc": null,
    "enrollment": null,
    "responseRate": 0.135,
    "responseRateAdjusted": null,
    "lowResponseRateIndicator": true,
    "numberOfSectionsEvaluated": 1,
    "courseOverallMean": 4.43,
    "courseOverallMeanAdjusted": null,
    "courseOverallSD": 0.65,
    "courseOverallSDAdjusted": null,
    "instructorOverallMean": 4.64,
    "instructorOverallMeanAdjusted": null,
    "instructorOverallSD": 0.5,
    "instructorOverallSDAdjusted": null
  },
  {
    "year": "23-24",
    "term": "SUMMER",
    "levelOfStatistics": "Section",
    "school": "SSCI",
    "department": "PHYS",
    "courseGroup": "PHYS",
    "courseNumber": "1002",
    "section": "L1",
    "courseCode": "23-24-SUMMER-PHYS-1002",
    "sectionCode": "23-24-SUMMER-PHYS-1002-L1",
    "surveyName": null,
    "instructorName": null,
    "instructorItsc": null,
    "enrollment": 104,
    "responseRate": 0.135,
    "responseRateAdjusted": null,
    "lowResponseRateIndicator": true,
    "numberOfSectionsEvaluated": null,
    "courseOverallMean": 4.43,
    "courseOverallMeanAdjusted": null,
    "courseOverallSD": 0.65,
    "courseOverallSDAdjusted": null,
    "instructorOverallMean": 4.64,
    "instructorOverallMeanAdjusted": null,
    "instructorOverallSD": 0.5,
    "instructorOverallSDAdjusted": null
  },
  {
    "year": "23-24",
    "term": "SUMMER",
    "levelOfStatistics": "Instructor",
    "school": "SSCI",
    "department": "PHYS",
    "courseGroup": "PHYS",
    "courseNumber": "1002",
    "section": "L1",
    "courseCode": "23-24-SUMMER-PHYS-1002",
    "sectionCode": "23-24-SUMMER-PHYS-1002-L1",
    "surveyName": "23-24-SUMMER-PHYS-1002-L1-SI",
    "instructorName": "CHEN, Tian Wen",
    "instructorItsc": "twchen",
    "enrollment": 104,
    "responseRate": 0.135,
    "responseRateAdjusted": 0.115,
    "lowResponseRateIndicator": true,
    "numberOfSectionsEvaluated": null,
    "courseOverallMean": 4.43,
    "courseOverallMeanAdjusted": 4.5,
    "courseOverallSD": 0.65,
    "courseOverallSDAdjusted": 0.52,
    "instructorOverallMean": 4.64,
    "instructorOverallMeanAdjusted": 4.67,
    "instructorOverallSD": 0.5,
    "instructorOverallSDAdjusted": 0.49
  },
  {
    "year": "23-24",
    "term": "SUMMER",
    "levelOfStatistics": "Course",
    "school": "SSCI",
    "department": "PHYS",
    "courseGroup": "PHYS",
    "courseNumber": "1113",
    "section": null,
    "courseCode": "23-24-SUMMER-PHYS-1113",
    "sectionCode": null,
    "surveyName": null,
    "instructorName": null,
    "instructorItsc": null,
    "enrollment": null,
    "responseRate": 0.5,
    "responseRateAdjusted": null,
    "lowResponseRateIndicator": true,
    "numberOfSectionsEvaluated": 1,
    "courseOverallMean": 4.5,
    "courseOverallMeanAdjusted": null,
    "courseOverallSD": 0.71,
    "courseOverallSDAdjusted": null,
    "instructorOverallMean": 4,
    "instructorOverallMeanAdjusted": null,
    "instructorOverallSD": 0,
    "instructorOverallSDAdjusted": null
  },
  {
    "year": "23-24",
    "term": "SUMMER",
    "levelOfStatistics": "Section",
    "school": "SSCI",
    "department": "PHYS",
    "courseGroup": "PHYS",
    "courseNumber": "1113",
    "section": "T1",
    "courseCode": "23-24-SUMMER-PHYS-1113",
    "sectionCode": "23-24-SUMMER-PHYS-1113-T1",
    "surveyName": null,
    "instructorName": null,
    "instructorItsc": null,
    "enrollment": 4,
    "responseRate": 0.5,
    "responseRateAdjusted": null,
    "lowResponseRateIndicator": true,
    "numberOfSectionsEvaluated": null,
    "courseOverallMean": 4.5,
    "courseOverallMeanAdjusted": null,
    "courseOverallSD": 0.71,
    "courseOverallSDAdjusted": null,
    "instructorOverallMean": 4,
    "instructorOverallMeanAdjusted": null,
    "instructorOverallSD": 0,
    "instructorOverallSDAdjusted": null
  },
  {
    "year": "23-24",
    "term": "SUMMER",
    "levelOfStatistics": "Instructor",
    "school": "SSCI",
    "department": "PHYS",
    "courseGroup": "PHYS",
    "courseNumber": "1113",
    "section": "T1",
    "courseCode": "23-24-SUMMER-PHYS-1113",
    "sectionCode": "23-24-SUMMER-PHYS-1113-T1",
    "surveyName": "23-24-SUMMER-PHYS-1113-T1-SI",
    "instructorName": "PANT, Nidhi",
    "instructorItsc": "pantnidhi",
    "enrollment": 4,
    "responseRate": 0.5,
    "responseRateAdjusted": null,
    "lowResponseRateIndicator": true,
    "numberOfSectionsEvaluated": null,
    "courseOverallMean": 4.5,
    "courseOverallMeanAdjusted": null,
    "courseOverallSD": 0.71,
    "courseOverallSDAdjusted": null,
    "instructorOverallMean": 4,
    "instructorOverallMeanAdjusted": null,
    "instructorOverallSD": 0,
    "instructorOverallSDAdjusted": null
  },
  {
    "year": "23-24",
    "term": "SUMMER",
    "levelOfStatistics": "Course",
    "school": "SSCI",
    "department": "PHYS",
    "courseGroup": "PHYS",
    "courseNumber": "1114",
    "section": null,
    "courseCode": "23-24-SUMMER-PHYS-1114",
    "sectionCode": null,
    "surveyName": null,
    "instructorName": null,
    "instructorItsc": null,
    "enrollment": null,
    "responseRate": 0.271,
    "responseRateAdjusted": null,
    "lowResponseRateIndicator": true,
    "numberOfSectionsEvaluated": 1,
    "courseOverallMean": 4.08,
    "courseOverallMeanAdjusted": null,
    "courseOverallSD": 1.12,
    "courseOverallSDAdjusted": null,
    "instructorOverallMean": 4.38,
    "instructorOverallMeanAdjusted": null,
    "instructorOverallSD": 0.77,
    "instructorOverallSDAdjusted": null
  },
  {
    "year": "23-24",
    "term": "SUMMER",
    "levelOfStatistics": "Section",
    "school": "SSCI",
    "department": "PHYS",
    "courseGroup": "PHYS",
    "courseNumber": "1114",
    "section": "L1",
    "courseCode": "23-24-SUMMER-PHYS-1114",
    "sectionCode": "23-24-SUMMER-PHYS-1114-L1",
    "surveyName": null,
    "instructorName": null,
    "instructorItsc": null,
    "enrollment": 48,
    "responseRate": 0.271,
    "responseRateAdjusted": null,
    "lowResponseRateIndicator": true,
    "numberOfSectionsEvaluated": null,
    "courseOverallMean": 4.08,
    "courseOverallMeanAdjusted": null,
    "courseOverallSD": 1.12,
    "courseOverallSDAdjusted": null,
    "instructorOverallMean": 4.38,
    "instructorOverallMeanAdjusted": null,
    "instructorOverallSD": 0.77,
    "instructorOverallSDAdjusted": null
  },
  {
    "year": "23-24",
    "term": "SUMMER",
    "levelOfStatistics": "Instructor",
    "school": "SSCI",
    "department": "PHYS",
    "courseGroup": "PHYS",
    "courseNumber": "1114",
    "section": "L1",
    "courseCode": "23-24-SUMMER-PHYS-1114",
    "sectionCode": "23-24-SUMMER-PHYS-1114-L1",
    "surveyName": "23-24-SUMMER-PHYS-1114-L1-SI",
    "instructorName": "CHEUNG, Man Fung",
    "instructorItsc": "cheungmf",
    "enrollment": 48,
    "responseRate": 0.271,
    "responseRateAdjusted": 0.229,
    "lowResponseRateIndicator": true,
    "numberOfSectionsEvaluated": null,
    "courseOverallMean": 4.08,
    "courseOverallMeanAdjusted": 4.27,
    "courseOverallSD": 1.12,
    "courseOverallSDAdjusted": 0.65,
    "instructorOverallMean": 4.38,
    "instructorOverallMeanAdjusted": 4.45,
    "instructorOverallSD": 0.77,
    "instructorOverallSDAdjusted": 0.69
  },
  {
    "year": "23-24",
    "term": "SUMMER",
    "levelOfStatistics": "Course",
    "school": "SSCI",
    "department": "PHYS",
    "courseGroup": "PHYS",
    "courseNumber": "1115",
    "section": null,
    "courseCode": "23-24-SUMMER-PHYS-1115",
    "sectionCode": null,
    "surveyName": null,
    "instructorName": null,
    "instructorItsc": null,
    "enrollment": null,
    "responseRate": 0.714,
    "responseRateAdjusted": 0.619,
    "numberOfSectionsEvaluated": 1,
    "courseOverallMean": 4.47,
    "courseOverallMeanAdjusted": 4.46,
    "courseOverallSD": 0.52,
    "courseOverallSDAdjusted": 0.52,
    "instructorOverallMean": 4.53,
    "instructorOverallMeanAdjusted": 4.54,
    "instructorOverallSD": 0.52,
    "instructorOverallSDAdjusted": 0.52
  },
  {
    "year": "23-24",
    "term": "SUMMER",
    "levelOfStatistics": "Section",
    "school": "SSCI",
    "department": "PHYS",
    "courseGroup": "PHYS",
    "courseNumber": "1115",
    "section": "T1",
    "courseCode": "23-24-SUMMER-PHYS-1115",
    "sectionCode": "23-24-SUMMER-PHYS-1115-T1",
    "surveyName": null,
    "instructorName": null,
    "instructorItsc": null,
    "enrollment": 21,
    "responseRate": 0.714,
    "responseRateAdjusted": 0.619,
    "numberOfSectionsEvaluated": null,
    "courseOverallMean": 4.47,
    "courseOverallMeanAdjusted": 4.46,
    "courseOverallSD": 0.52,
    "courseOverallSDAdjusted": 0.52,
    "instructorOverallMean": 4.53,
    "instructorOverallMeanAdjusted": 4.54,
    "instructorOverallSD": 0.52,
    "instructorOverallSDAdjusted": 0.52
  },
  {
    "year": "23-24",
    "term": "SUMMER",
    "levelOfStatistics": "Instructor",
    "school": "SSCI",
    "department": "PHYS",
    "courseGroup": "PHYS",
    "courseNumber": "1115",
    "section": "T1",
    "courseCode": "23-24-SUMMER-PHYS-1115",
    "sectionCode": "23-24-SUMMER-PHYS-1115-T1",
    "surveyName": "23-24-SUMMER-PHYS-1115-T1-SI",
    "instructorName": "NG, Yee Fai",
    "instructorItsc": "phyfng",
    "enrollment": 21,
    "responseRate": 0.714,
    "responseRateAdjusted": 0.619,
    "numberOfSectionsEvaluated": null,
    "courseOverallMean": 4.47,
    "courseOverallMeanAdjusted": 4.46,
    "courseOverallSD": 0.52,
    "courseOverallSDAdjusted": 0.52,
    "instructorOverallMean": 4.53,
    "instructorOverallMeanAdjusted": 4.54,
    "instructorOverallSD": 0.52,
    "instructorOverallSDAdjusted": 0.52
  },
  {
    "year": "23-24",
    "term": "SUMMER",
    "levelOfStatistics": "Course",
    "school": "SSCI",
    "department": "MAFS",
    "courseGroup": "MAFS",
    "courseNumber": "5270",
    "section": null,
    "courseCode": "23-24-SUMMER-MAFS-5270",
    "sectionCode": null,
    "surveyName": null,
    "instructorName": null,
    "instructorItsc": null,
    "enrollment": null,
    "responseRate": 0.2,
    "responseRateAdjusted": 0.156,
    "lowResponseRateIndicator": true,
    "numberOfSectionsEvaluated": 1,
    "courseOverallMean": 4.67,
    "courseOverallMeanAdjusted": 4.71,
    "courseOverallSD": 0.5,
    "courseOverallSDAdjusted": 0.49,
    "instructorOverallMean": 4.78,
    "instructorOverallMeanAdjusted": 4.86,
    "instructorOverallSD": 0.44,
    "instructorOverallSDAdjusted": 0.38
  },
  {
    "year": "23-24",
    "term": "SUMMER",
    "levelOfStatistics": "Section",
    "school": "SSCI",
    "department": "MAFS",
    "courseGroup": "MAFS",
    "courseNumber": "5270",
    "section": "L1",
    "courseCode": "23-24-SUMMER-MAFS-5270",
    "sectionCode": "23-24-SUMMER-MAFS-5270-L1",
    "surveyName": null,
    "instructorName": null,
    "instructorItsc": null,
    "enrollment": 45,
    "responseRate": 0.2,
    "responseRateAdjusted": 0.156,
    "lowResponseRateIndicator": true,
    "numberOfSectionsEvaluated": null,
    "courseOverallMean": 4.67,
    "courseOverallMeanAdjusted": 4.71,
    "courseOverallSD": 0.5,
    "courseOverallSDAdjusted": 0.49,
    "instructorOverallMean": 4.78,
    "instructorOverallMeanAdjusted": 4.86,
    "instructorOverallSD": 0.44,
    "instructorOverallSDAdjusted": 0.38
  },
  {
    "year": "23-24",
    "term": "SUMMER",
    "levelOfStatistics": "Instructor",
    "school": "SSCI",
    "department": "MAFS",
    "courseGroup": "MAFS",
    "courseNumber": "5270",
    "section": "L1",
    "courseCode": "23-24-SUMMER-MAFS-5270",
    "sectionCode": "23-24-SUMMER-MAFS-5270-L1",
    "surveyName": "23-24-SUMMER-MAFS-5270-L1-SI",
    "instructorName": "CHOU, Hongsong",
    "instructorItsc": "mahchou",
    "enrollment": 45,
    "responseRate": 0.2,
    "responseRateAdjusted": 0.156,
    "lowResponseRateIndicator": true,
    "numberOfSectionsEvaluated": null,
    "courseOverallMean": 4.67,
    "courseOverallMeanAdjusted": 4.71,
    "courseOverallSD": 0.5,
    "courseOverallSDAdjusted": 0.49,
    "instructorOverallMean": 4.78,
    "instructorOverallMeanAdjusted": 4.86,
    "instructorOverallSD": 0.44,
    "instructorOverallSDAdjusted": 0.38
  },
  {
    "year": "23-24",
    "term": "SUMMER",
    "levelOfStatistics": "Course",
    "school": "SSCI",
    "department": "MAFS",
    "courseGroup": "MAFS",
    "courseNumber": "5360",
    "section": null,
    "courseCode": "23-24-SUMMER-MAFS-5360",
    "sectionCode": null,
    "surveyName": null,
    "instructorName": null,
    "instructorItsc": null,
    "enrollment": null,
    "responseRate": 0.143,
    "responseRateAdjusted": 0.095,
    "lowResponseRateIndicator": true,
    "numberOfSectionsEvaluated": 1,
    "courseOverallMean": 4.83,
    "courseOverallMeanAdjusted": 5,
    "courseOverallSD": 0.41,
    "courseOverallSDAdjusted": 0,
    "instructorOverallMean": 4.83,
    "instructorOverallMeanAdjusted": 5,
    "instructorOverallSD": 0.41,
    "instructorOverallSDAdjusted": 0
  },
  {
    "year": "23-24",
    "term": "SUMMER",
    "levelOfStatistics": "Section",
    "school": "SSCI",
    "department": "MAFS",
    "courseGroup": "MAFS",
    "courseNumber": "5360",
    "section": "L1",
    "courseCode": "23-24-SUMMER-MAFS-5360",
    "sectionCode": "23-24-SUMMER-MAFS-5360-L1",
    "surveyName": null,
    "instructorName": null,
    "instructorItsc": null,
    "enrollment": 42,
    "responseRate": 0.143,
    "responseRateAdjusted": 0.095,
    "lowResponseRateIndicator": true,
    "numberOfSectionsEvaluated": null,
    "courseOverallMean": 4.83,
    "courseOverallMeanAdjusted": 5,
    "courseOverallSD": 0.41,
    "courseOverallSDAdjusted": 0,
    "instructorOverallMean": 4.83,
    "instructorOverallMeanAdjusted": 5,
    "instructorOverallSD": 0.41,
    "instructorOverallSDAdjusted": 0
  },
  {
    "year": "23-24",
    "term": "SUMMER",
    "levelOfStatistics": "Instructor",
    "school": "SSCI",
    "department": "MAFS",
    "courseGroup": "MAFS",
    "courseNumber": "5360",
    "section": "L1",
    "courseCode": "23-24-SUMMER-MAFS-5360",
    "sectionCode": "23-24-SUMMER-MAFS-5360-L1",
    "surveyName": "23-24-SUMMER-MAFS-5360-L1-SI",
    "instructorName": "CHOU, Hongsong",
    "instructorItsc": "mahchou",
    "enrollment": 42,
    "responseRate": 0.143,
    "responseRateAdjusted": 0.095,
    "lowResponseRateIndicator": true,
    "numberOfSectionsEvaluated": null,
    "courseOverallMean": 4.83,
    "courseOverallMeanAdjusted": 5,
    "courseOverallSD": 0.41,
    "courseOverallSDAdjusted": 0,
    "instructorOverallMean": 4.83,
    "instructorOverallMeanAdjusted": 5,
    "instructorOverallSD": 0.41,
    "instructorOverallSDAdjusted": 0
  }
]